django_transaction_signals_do_not_use-1.0.dist-info/DESCRIPTION.rst
django_transaction_signals_do_not_use-1.0.dist-info/METADATA
django_transaction_signals_do_not_use-1.0.dist-info/pydist.json
django_transaction_signals_do_not_use-1.0.dist-info/RECORD
django_transaction_signals_do_not_use-1.0.dist-info/top_level.txt
django_transaction_signals_do_not_use-1.0.dist-info/WHEEL
transaction_signals/__init__.py
transaction_signals/monkey.py
transaction_signals/signals.py
transaction_signals/test_settings.py
transaction_signals/tests.py
