Metadata-Version: 2.0
Name: django-transaction-signals-do-not-use
Version: 1.0
Summary: Transaction signals for Django. Don't use this!
Home-page: https://github.com/aaugustin/django-transaction-signals
Author: Aymeric Augustin
Author-email: aymeric.augustin@m4x.org
License: WTFPL
Download-URL: http://pypi.python.org/pypi/django-transaction-signals-do-not-use
Platform: all
Classifier: Development Status :: 5 - Production/Stable
Classifier: Environment :: Web Environment
Classifier: Framework :: Django
Classifier: Intended Audience :: Developers
Classifier: License :: OSI Approved :: BSD License
Classifier: Operating System :: OS Independent
Classifier: Programming Language :: Python
Classifier: Programming Language :: Python :: 2
Classifier: Programming Language :: Python :: 2.6
Classifier: Programming Language :: Python :: 2.7
Classifier: Programming Language :: Python :: 3
Classifier: Programming Language :: Python :: 3.2
Classifier: Programming Language :: Python :: 3.3
